podigeeconnector/__init__.py
podigeeconnector/__main__.py
podigeeconnector/connector.py
podigeeconnector-0.4.0.dist-info/LICENSE
podigeeconnector-0.4.0.dist-info/METADATA
podigeeconnector-0.4.0.dist-info/WHEEL
podigeeconnector-0.4.0.dist-info/entry_points.txt
podigeeconnector-0.4.0.dist-info/top_level.txt
podigeeconnector-0.4.0.dist-info/RECORD
