Metadata-Version: 2.1
Name: podigeeconnector
Version: 0.4.0
Summary: Podigee Connector for Podcast Data
Author: Open Podcast
License: MIT
License-File: LICENSE
Requires-Dist: requests
Requires-Dist: loguru
Requires-Dist: PyYAML
Requires-Dist: tenacity
Requires-Dist: beautifulsoup4
